{"all": {"nodes": [{"atom": 0, "group": 2, "image_address": "output/fd0c11c95c8614cfb4b76a28208d61f9/01.mov/000.gif", "name": "0.2.447", "image_width": 53, "image_height": 30, "HasFace": false, "clip_len": 447 
}, 
{"atom": 1, "group": 38, "image_address": "https://bitbucket.org/viddai/viddai.bitbucket.io/raw/503d77de321331dd70d75dac0d766165719fad7f/output/fd0c11c95c8614cfb4b76a28208d61f9/01.mov/001.gif", "name": "1.38.9369", "image_width": 53, "image_height": 30, "HasFace": false, "clip_len": 8922 
}, {"atom": 2, "group": 39, "image_address": "output/fd0c11c95c8614cfb4b76a28208d61f9/01.mov/002.gif", "name": "2.39.9566", "image_width": 53, "image_height": 30, "HasFace": false, "clip_len": 197 
}, 
{"atom": 3, "group": 45, "image_address": "output/fd0c11c95c8614cfb4b76a28208d61f9/01.mov/003.gif", "name": "3.45.11128", "image_width": 53, "image_height": 30, "HasFace": false, "clip_len": 1562 
}, 
{"atom": 4, "group": 60, "image_address": "output/fd0c11c95c8614cfb4b76a28208d61f9/01.mov/004.gif", "name": "4.60.14475", "image_width": 53, "image_height": 30, "HasFace": false, "clip_len": 3347 
}, 
{"atom": 5, "group": 61, "image_address": "output/fd0c11c95c8614cfb4b76a28208d61f9/01.mov/005.gif", "name": "5.61.14478", "image_width": 53, "image_height": 30, "HasFace": false, "clip_len": 3 
}, 
{"atom": 6, "group": 61, "image_address": "output/fd0c11c95c8614cfb4b76a28208d61f9/01.mov/006.gif", "name": "6.61.14508", "image_width": 53, "image_height": 30, "HasFace": false, "clip_len": 30 
}, 
{"atom": 7, "group": 106, "image_address": "https://bitbucket.org/viddai/viddai.bitbucket.io/raw/503d77de321331dd70d75dac0d766165719fad7f/output/fd0c11c95c8614cfb4b76a28208d61f9/01.mov/007.gif", "name": "7.106.25258", "image_width": 53, "image_height": 30, "HasFace": false, "clip_len": 10750
}, 
{"atom": 8, "group": 117, "image_address": "output/fd0c11c95c8614cfb4b76a28208d61f9/01.mov/008.gif", "name": "8.117.27857", "image_width": 53, "image_height": 30, "HasFace": false, "clip_len": 2599 
}, 
{"atom": 9, "group": 142, "image_address": "https://bitbucket.org/viddai/viddai.bitbucket.io/raw/503d77de321331dd70d75dac0d766165719fad7f/output/fd0c11c95c8614cfb4b76a28208d61f9/01.mov/009.gif", "name": "9.142.33677", "image_width": 53, "image_height": 30, "HasFace": false, "clip_len": 5820 
}, 
{"atom": 10, "group": 145, "image_address": "output/fd0c11c95c8614cfb4b76a28208d61f9/01.mov/010.gif", "name": "10.145.34412", "image_width": 53, "image_height": 30, "HasFace": false, "clip_len": 735 
}, 
{"atom": 11, "group": 148, "image_address": "output/fd0c11c95c8614cfb4b76a28208d61f9/01.mov/011.gif", "name": "11.148.35060", "image_width": 53, "image_height": 30, "HasFace": false, "clip_len": 648 
}, 
{"atom": 12, "group": 161, "image_address": "output/fd0c11c95c8614cfb4b76a28208d61f9/01.mov/012.gif", "name": "12.161.37763", "image_width": 53, "image_height": 30, "HasFace": false, "clip_len": 2703 
},
 {"atom": 13, "group": 178, "image_address": "output/fd0c11c95c8614cfb4b76a28208d61f9/01.mov/013.gif", "name": "13.178.41838", "image_width": 53, "image_height": 30, "HasFace": false, "clip_len": 4075
},
 {"atom": 14, "group": 182, "image_address": "output/fd0c11c95c8614cfb4b76a28208d61f9/01.mov/014.gif", "name": "14.182.42573", "image_width": 53, "image_height": 30, "HasFace": false, "clip_len": 735
}, 
{"atom": 15, "group": 230, "image_address": "https://bitbucket.org/viddai/viddai.bitbucket.io/raw/503d77de321331dd70d75dac0d766165719fad7f/output/fd0c11c95c8614cfb4b76a28208d61f9/01.mov/015.gif", "name": "15.230.53895", "image_width": 53, "image_height": 30, "HasFace": false, "clip_len": 11322
}, 
{"atom": 16, "group": 237, "image_address": "output/fd0c11c95c8614cfb4b76a28208d61f9/01.mov/016.gif", "name": "16.237.55433", "image_width": 53, "image_height": 30, "HasFace": false, "clip_len": 1538
}, 
{"atom": 17, "group": 239, "image_address": "output/fd0c11c95c8614cfb4b76a28208d61f9/01.mov/017.gif", "name": "17.239.55688", "image_width": 53, "image_height": 30, "HasFace": false, "clip_len": 255
}
], 
"links": []}, 
"face": {"nodes": [], "links": []}, 
"vary": {"nodes": [{"atom": 1, "group": 38, "image_address": "output/fd0c11c95c8614cfb4b76a28208d61f9/01.mov/001.gif", "name": "1.38.9369", "image_width": 53, "image_height": 30, "HasFace": false, "clip_len": 8922 
}, 
{"atom": 4, "group": 60, "image_address": "output/fd0c11c95c8614cfb4b76a28208d61f9/01.mov/004.gif", "name": "4.60.14475", "image_width": 53, "image_height": 30, "HasFace": false, "clip_len": 3347 
},
 {"atom": 6, "group": 61, "image_address": "output/fd0c11c95c8614cfb4b76a28208d61f9/01.mov/006.gif", "name": "6.61.14508", "image_width": 53, "image_height": 30, "HasFace": false, "clip_len": 30 
},
 {"atom": 13, "group": 178, "image_address": "output/fd0c11c95c8614cfb4b76a28208d61f9/01.mov/013.gif", "name": "13.178.41838", "image_width": 53, "image_height": 30, "HasFace": false, "clip_len": 4075
},
 {"atom": 15, "group": 230, "image_address": "output/fd0c11c95c8614cfb4b76a28208d61f9/01.mov/015.gif", "name": "15.230.53895", "image_width": 53, "image_height": 30, "HasFace": false, "clip_len": 11322
}], "links": []}
}
